ShitMountainGenerator/__init__.py
ShitMountainGenerator/common.py
ShitMountainGenerator/exceptions.py
ShitMountainGenerator/select_statement.py
ShitMountainGenerator/shitter.py
ShitMountainGenerator/template.py
ShitMountainGenerator/template_parser.py
shit_mountain_generator-1.0.2.dist-info/LICENSE
shit_mountain_generator-1.0.2.dist-info/METADATA
shit_mountain_generator-1.0.2.dist-info/WHEEL
shit_mountain_generator-1.0.2.dist-info/top_level.txt
shit_mountain_generator-1.0.2.dist-info/RECORD
