Metadata-Version: 2.1
Name: shit-mountain-generator
Version: 1.0.2
Summary: A general purpose template driven code generator  
Home-page: https://github.com/guo40020/shit_mountain_generator
Author: Kelly
Author-email: 
License: MIT
Platform: UNKNOWN
License-File: LICENSE
